dotenv_flow/__init__.py
dotenv_flow/py.typed
dotenv_flow-0.4.0.dist-info/METADATA
dotenv_flow-0.4.0.dist-info/WHEEL
dotenv_flow-0.4.0.dist-info/RECORD
