Metadata-Version: 2.1
Name: dotenv-flow
Version: 0.4.0
Summary: Like the dotenv-flow NodeJS library, for Python
Home-page: https://github.com/ChacheGS/dotenv_flow
License: WTFPL
Keywords: environment variables,deployments,settings,env,dotenv,configurations,python
Author: Carlos Gonzalez
Author-email: gonsa.carlos@gmail.com
Requires-Python: >=3.8,<4.0
Classifier: License :: Other/Proprietary License
Classifier: Programming Language :: Python :: 3
Classifier: Programming Language :: Python :: 3.8
Classifier: Programming Language :: Python :: 3.9
Classifier: Programming Language :: Python :: 3.10
Classifier: Programming Language :: Python :: 3.11
Requires-Dist: python-dotenv (>=1.0,<2.0)
Project-URL: Repository, https://github.com/ChacheGS/dotenv_flow
